quantlib_risks-1.33.3.dist-info/RECORD
quantlib_risks-1.33.3.dist-info/WHEEL
quantlib_risks-1.33.3.dist-info/METADATA
QuantLib_Risks/_QuantLib_Risks.cpython-310-darwin.so
QuantLib_Risks/__init__.py
QuantLib_Risks/QuantLib_Risks.py
QuantLib_Risks/.dylibs/libQuantLib.1.33.0.dylib
